README.md
sanic_sslify.py
setup.py
Sanic_SSLify.egg-info/PKG-INFO
Sanic_SSLify.egg-info/SOURCES.txt
Sanic_SSLify.egg-info/dependency_links.txt
Sanic_SSLify.egg-info/not-zip-safe
Sanic_SSLify.egg-info/requires.txt
Sanic_SSLify.egg-info/top_level.txt