Metadata-Version: 1.1
Name: Sanic-SSLify
Version: 0.1.1
Summary: Force SSL on your Sanic app.
Home-page: https://github.com/dzqdzq/Sanic-sslify
Author: dzqdzq
Author-email: 1246747572@qq.com
License: MIT
Platform: any
Classifier: Environment :: Web Environment
Classifier: Intended Audience :: Developers
Classifier: License :: OSI Approved :: BSD License
Classifier: Operating System :: OS Independent
Classifier: Programming Language :: Python
Classifier: Programming Language :: Python :: 3
Classifier: Topic :: Internet :: WWW/HTTP :: Dynamic Content
Classifier: Topic :: Software Development :: Libraries :: Python Modules
